<?xml version="1.0" encoding="utf-8" ?><dwsync><file name="audio.gif" server="ftp.framedcollegefootballart.com/www/" local="3297945345" remote="12001325072" /><file name="embedded.png" server="ftp.framedcollegefootballart.com/www/" local="3339229422" remote="12001325072" /><file name="image.gif" server="ftp.framedcollegefootballart.com/www/" local="3297945345" remote="12001325072" /><file name="media.gif" server="ftp.framedcollegefootballart.com/www/" local="3297945345" remote="12001325072" /><file name="more_bug.gif" server="ftp.framedcollegefootballart.com/www/" local="3284647846" remote="12001325072" /><file name="page.gif" server="ftp.framedcollegefootballart.com/www/" local="3284647846" remote="12001325072" /><file name="page_bug.gif" server="ftp.framedcollegefootballart.com/www/" local="3284647846" remote="12001325072" /><file name="trans.gif" server="ftp.framedcollegefootballart.com/www/" local="3284647846" remote="12001325072" /><file name="video.gif" server="ftp.framedcollegefootballart.com/www/" local="3297945345" remote="12001325072" /></dwsync>